simplepcap/__init__.py
simplepcap/enum.py
simplepcap/exceptions.py
simplepcap/parser.py
simplepcap/types.py
simplepcap/parsers/__init__.py
simplepcap/parsers/default/__init__.py
simplepcap/parsers/default/iterator.py
simplepcap/parsers/default/parser.py
simplepcap-0.1.9.dist-info/LICENSE
simplepcap-0.1.9.dist-info/METADATA
simplepcap-0.1.9.dist-info/WHEEL
simplepcap-0.1.9.dist-info/top_level.txt
simplepcap-0.1.9.dist-info/RECORD
