Metadata-Version: 2.1
Name: simplepcap
Version: 0.1.9
Summary: A simple pcap library for Python
Author-email: Illia Chaban <ic-it@mail.com>
License: MIT License
Project-URL: Homepage, https://ic-it.github.io/simplepcap/
Project-URL: Documentation, https://ic-it.github.io/simplepcap/reference/
Project-URL: Bug Reports, https://github.com/ic-it/simplepcap/issues
Project-URL: Source Code, https://github.com/ic-it/simplepcap
Keywords: pcap,development,networking,python
Classifier: Development Status :: 3 - Alpha
Classifier: Intended Audience :: Developers
Classifier: License :: OSI Approved :: MIT License
Classifier: Operating System :: OS Independent
Classifier: Programming Language :: Python :: 3.10
Classifier: Programming Language :: Python :: 3.11
Classifier: Programming Language :: Python :: 3 :: Only
Requires-Python: >=3.10
License-File: LICENSE
Provides-Extra: dev
Requires-Dist: black ==23.9.1 ; extra == 'dev'
Requires-Dist: flake8 ==6.1.0 ; extra == 'dev'
Requires-Dist: Flake8-pyproject ==1.2.3 ; extra == 'dev'
Requires-Dist: flake8-function-order ==0.0.5 ; extra == 'dev'
Requires-Dist: mkdocs ==1.5.2 ; extra == 'dev'
Requires-Dist: mkdocstrings[python] ==0.23.0 ; extra == 'dev'
Requires-Dist: mkdocs-material ==9.3.1 ; extra == 'dev'
Requires-Dist: pytest ==7.4.2 ; extra == 'dev'
Provides-Extra: docs
Requires-Dist: mkdocs ==1.5.2 ; extra == 'docs'
Requires-Dist: mkdocstrings[python] ==0.23.0 ; extra == 'docs'
Requires-Dist: mkdocs-material ==9.3.1 ; extra == 'docs'
Provides-Extra: lint
Requires-Dist: flake8 ==6.1.0 ; extra == 'lint'
Requires-Dist: Flake8-pyproject ==1.2.3 ; extra == 'lint'
Requires-Dist: flake8-function-order ==0.0.5 ; extra == 'lint'
Provides-Extra: publish
Requires-Dist: build ==1.0.3 ; extra == 'publish'
Provides-Extra: test
Requires-Dist: pytest ==7.4.2 ; extra == 'test'
